setup.py
touchpaper/__init__.py
touchpaper/_version.py
touchpaper/config.py
touchpaper/instance.py
touchpaper/main.py
touchpaper/prompts.py
touchpaper/utils.py
touchpaper.egg-info/PKG-INFO
touchpaper.egg-info/SOURCES.txt
touchpaper.egg-info/dependency_links.txt
touchpaper.egg-info/entry_points.txt
touchpaper.egg-info/requires.txt
touchpaper.egg-info/top_level.txt