Metadata-Version: 1.0
Name: touchpaper
Version: 0.2.8
Summary: A command-line utility to quickly launch EC2 instances. A tasty accompaniment to Fabric.
Home-page: http://github.com/BigglesZX/touchpaper
Author: James Tiplady
Author-email: UNKNOWN
License: UNKNOWN
Platform: UNKNOWN
Classifier: Development Status :: 4 - Beta
Classifier: Environment :: Console
Classifier: Intended Audience :: System Administrators
Classifier: Operating System :: MacOS :: MacOS X
Classifier: Operating System :: Unix
Classifier: Operating System :: POSIX
Classifier: Programming Language :: Python
Classifier: Programming Language :: Python :: 2.6
Classifier: Programming Language :: Python :: 2.7
Classifier: Topic :: System :: Systems Administration
Classifier: Topic :: Utilities
